flask_recaptcha.py
setup.cfg
setup.py
Flask_reCaptcha.egg-info/PKG-INFO
Flask_reCaptcha.egg-info/SOURCES.txt
Flask_reCaptcha.egg-info/dependency_links.txt
Flask_reCaptcha.egg-info/not-zip-safe
Flask_reCaptcha.egg-info/pbr.json
Flask_reCaptcha.egg-info/requires.txt
Flask_reCaptcha.egg-info/top_level.txt