Metadata-Version: 1.1
Name: Flask-reCaptcha
Version: 0.2
Summary: 
